mlmodels/__init__.py
mlmodels/data.py
mlmodels/distri_torch.py
mlmodels/distri_torch_mpirun.sh
mlmodels/models.py
mlmodels/optim.py
mlmodels/pipeline.py
mlmodels/util.py
mlmodels/ztest.py
mlmodels/config/readme.md
mlmodels/model_dev/__init__.py
mlmodels/model_dev/ml_mosaic.py
mlmodels/model_dev/mytest.py
mlmodels/model_flow/__init__.py
mlmodels/model_flow/mlflow_run.py
mlmodels/model_gluon/README.md
mlmodels/model_gluon/__init__.py
mlmodels/model_gluon/gluon_automl.json
mlmodels/model_gluon/gluon_automl.py
mlmodels/model_gluon/gluon_deepar.py
mlmodels/model_gluon/gluon_ffn.py
mlmodels/model_gluon/gluon_prophet.json
mlmodels/model_gluon/gluon_prophet.py
mlmodels/model_gluon/util.py
mlmodels/model_gluon/util_autogluon.py
mlmodels/model_keras/00_template_keras.py
mlmodels/model_keras/01_deep_ctr.json
mlmodels/model_keras/01_deepctr.py
mlmodels/model_keras/02_cnn.py
mlmodels/model_keras/__init__.py
mlmodels/model_keras/preprocess.py
mlmodels/model_keras/util.py
mlmodels/model_sklearn/__init__.py
mlmodels/model_sklearn/model.py
mlmodels/model_tch/__init__.py
mlmodels/model_tch/cnn_classifier.py
mlmodels/model_tch/data_prep.py
mlmodels/model_tch/mlp.py
mlmodels/model_tch/nbeats.py
mlmodels/model_tch/sentence_transformer.py
mlmodels/model_tch/transformer_classifier.py
mlmodels/model_tch/util_transformer.py
mlmodels/model_tch/nbeats/__init__.py
mlmodels/model_tch/nbeats/data.py
mlmodels/model_tch/nbeats/model.py
mlmodels/model_tch/nbeats/nbeats.py
mlmodels/model_tch/nbeats/nbeats_sample.py
mlmodels/model_tch/nbeats/trainer.py
mlmodels/model_tch/zdocs/Richer Sentence Embeddings using Sentence-BERT — Part I.pdf
mlmodels/model_tf/10_encoder_vanilla.py
mlmodels/model_tf/11_bidirectional_vanilla.py
mlmodels/model_tf/12_vanilla_2path.py
mlmodels/model_tf/13_lstm_seq2seq.py
mlmodels/model_tf/14_lstm_attention.py
mlmodels/model_tf/15_lstm_seq2seq_attention.py
mlmodels/model_tf/16_lstm_seq2seq_bidirectional.py
mlmodels-0.38.1.dist-info/METADATA
mlmodels-0.38.1.dist-info/RECORD
mlmodels-0.38.1.dist-info/WHEEL
mlmodels-0.38.1.dist-info/entry_points.txt
mlmodels-0.38.1.dist-info/top_level.txt
