Metadata-Version: 2.1
Name: mlmodels
Version: 0.38.1
Summary: Generic model API, Model Zoo in Tensorflow, Keras, Pytorch, Hyperparamter search
Home-page: https://github.com/arita37/mlmodels
Author: Kevin Noel
Author-email: brookm291@gmail.com
License: UNKNOWN
Keywords: Machine Learning Interface library
Platform: UNKNOWN
Classifier: Development Status :: 3 - Alpha
Classifier: Intended Audience :: End Users/Desktop
Classifier: Intended Audience :: Developers
Classifier: Intended Audience :: Science/Research
Classifier: License :: OSI Approved :: Apache Software License
Classifier: Programming Language :: Python :: 3
Classifier: Programming Language :: Python :: 3.6
Classifier: Topic :: Scientific/Engineering
Classifier: Topic :: Scientific/Engineering :: Artificial Intelligence
Classifier: Topic :: Software Development :: Libraries
Classifier: Topic :: Software Development :: Libraries :: Python Modules
Classifier: Topic :: Scientific/Engineering :: Information Analysis
Classifier: Environment :: Console
Classifier: Environment :: Web Environment
Classifier: Operating System :: POSIX
Classifier: Operating System :: MacOS :: MacOS X
Requires-Python: >=3.6
Requires-Dist: numpy (>=1.16.4)
Requires-Dist: pandas (>=0.24.2)
Requires-Dist: scipy (>=1.3.0)
Requires-Dist: scikit-learn (>=0.21.2)
Requires-Dist: numexpr (>=2.6.8)
Requires-Dist: sqlalchemy (>=1.3.8)
Requires-Dist: tensorflow (>=1.14.0)
Requires-Dist: pytorch (>=0.4.0)
Requires-Dist: optuna
Requires-Dist: lightgbm
Requires-Dist: mlflow
